memorecall/__init__.py
memorecall/core.py
memorecall/ingestion.py
memorecall/py.typed
memorecall-0.1.1.dist-info/METADATA
memorecall-0.1.1.dist-info/WHEEL
memorecall-0.1.1.dist-info/licenses/LICENSE
memorecall-0.1.1.dist-info/RECORD
