Metadata-Version: 2.4
Name: memorecall
Version: 0.1.1
Summary: A memory and recall enhancement library for AI agents.
Project-URL: Homepage, https://github.com/HoseynAAmiri/memorecall
Project-URL: Repository, https://github.com/HoseynAAmiri/memorecall
Project-URL: Issues, https://github.com/HoseynAAmiri/memorecall/issues
Author-email: Hoseyn Amiri <aamirihoseyn@gmail.com>
License: MIT
License-File: LICENSE
Keywords: agent,ai,memory,recall
Requires-Python: >=3.13
